mkdocs_enumerate_headings_plugin/__init__.py
mkdocs_enumerate_headings_plugin/exclude.py
mkdocs_enumerate_headings_plugin/heading.py
mkdocs_enumerate_headings_plugin/html_page.py
mkdocs_enumerate_headings_plugin/plugin.py
mkdocs_enumerate_headings_plugin-0.6.2.dist-info/LICENSE
mkdocs_enumerate_headings_plugin-0.6.2.dist-info/METADATA
mkdocs_enumerate_headings_plugin-0.6.2.dist-info/WHEEL
mkdocs_enumerate_headings_plugin-0.6.2.dist-info/entry_points.txt
mkdocs_enumerate_headings_plugin-0.6.2.dist-info/top_level.txt
mkdocs_enumerate_headings_plugin-0.6.2.dist-info/RECORD
