Metadata-Version: 2.1
Name: mkdocs-enumerate-headings-plugin
Version: 0.6.2
Summary: MkDocs Plugin to enumerate the headings (h1-h6) across site pages
Home-page: https://github.com/timvink/mkdocs-enumerate-headings-plugin.git
Author: timvink
Author-email: vinktim@gmail.com
License: MIT
Keywords: mkdocs enumerate headings plugin
Classifier: Intended Audience :: Developers
Classifier: Intended Audience :: Information Technology
Classifier: License :: OSI Approved :: MIT License
Classifier: Programming Language :: Python
Classifier: Programming Language :: Python :: 3 :: Only
Classifier: Programming Language :: Python :: 3.8
Classifier: Programming Language :: Python :: 3.9
Classifier: Programming Language :: Python :: 3.10
Classifier: Programming Language :: Python :: 3.11
Requires-Python: >=3.7
License-File: LICENSE
Requires-Dist: mkdocs >=1.0.4
Requires-Dist: beautifulsoup4 >=4.9.0
